pyalltools.py
pyalltools-3.2.2.dist-info/METADATA
pyalltools-3.2.2.dist-info/WHEEL
pyalltools-3.2.2.dist-info/top_level.txt
pyalltools-3.2.2.dist-info/RECORD
