Metadata-Version: 2.1
Name: pyalltools
Version: 3.2.2
Summary: Library containing various tools that are required by programmers frequently
Home-page: https://techinfoak.wixsite.com/tech-info
Author: Anupam Kanoongo
Author-email: programmer.tiak@gmail.com
License: MIT
Project-URL: Our Website, https://techinfoak.wixsite.com/tech-info
Project-URL: Our YT Handle, https://youtube.com/@techinfoak
Classifier: Programming Language :: Python :: 3
Classifier: License :: OSI Approved :: MIT License
Classifier: Operating System :: OS Independent
Requires-Python: >=3.6
Requires-Dist: fetchify
